LICENSE
MANIFEST.in
README.md
setup.cfg
setup.py
choria_external/__init__.py
choria_external/base.py
choria_external/config.py
choria_external/dispatcher.py
choria_external/exceptions.py
choria_external/protocol.py
choria_external/version.py
py_choria_external.egg-info/PKG-INFO
py_choria_external.egg-info/SOURCES.txt
py_choria_external.egg-info/dependency_links.txt
py_choria_external.egg-info/requires.txt
py_choria_external.egg-info/top_level.txt