Metadata-Version: 2.1
Name: py-choria-external
Version: 0.2.0
Summary: A library for implementing Choria External RPC in python
Home-page: https://github.com/optiz0r/py-choria-external
Author: Ben Roberts
Author-email: me@benroberts.net
License: UNKNOWN
Platform: UNKNOWN
Classifier: Programming Language :: Python :: 2
Classifier: Programming Language :: Python :: 3
Classifier: License :: OSI Approved :: Apache Software License
Classifier: Operating System :: OS Independent
Requires-Python: >=2.6
License-File: LICENSE
